src/__init__.py
pysprint_abBay_analysis-0.0.1.dist-info/METADATA
pysprint_abBay_analysis-0.0.1.dist-info/WHEEL
pysprint_abBay_analysis-0.0.1.dist-info/top_level.txt
pysprint_abBay_analysis-0.0.1.dist-info/RECORD
