Metadata-Version: 2.1
Name: pysprint-abBay-analysis
Version: 0.0.1
Summary: Bayesian AB test package
Home-page: https://github.com/AngelaO/Bayesian-ABTest
Author: Gender Minorities Py Sprints
Author-email: author@example.com
License: UNKNOWN
Platform: any
Classifier: Programming Language :: Python :: 3
Classifier: License :: OSI Approved :: MIT License
Classifier: Operating System :: OS Independent
Requires-Python: >=3.3
